json_with_decimals/__init__.py
json_with_decimals/decoder.py
json_with_decimals/encoder.py
json_with_decimals/scanner.py
json_with_decimals/tool.py
json_with_decimals-0.1.0.dist-info/LICENSE
json_with_decimals-0.1.0.dist-info/METADATA
json_with_decimals-0.1.0.dist-info/WHEEL
json_with_decimals-0.1.0.dist-info/top_level.txt
json_with_decimals-0.1.0.dist-info/RECORD
