Metadata-Version: 2.1
Name: json_with_decimals
Version: 0.1.0
Summary: A fork of Python's built-in JSON module, but with added support for decimal.Decimal objects
Author-email: Christopher Ashford <christopherash0605@gmail.com>
Project-URL: repository, https://github.com/Kris-0605/json_with_decimals
Keywords: json,decimal
Classifier: Development Status :: 3 - Alpha
Classifier: Intended Audience :: Developers
Classifier: Natural Language :: English
Classifier: Programming Language :: Python
Classifier: Topic :: File Formats
License-File: LICENSE
